{
  "id": "retained-placenta",
  "name": "Sót nhau ở dê",
  "species": "goat",
  "group": "reproductive",

  "summary": "Sót nhau là tình trạng nhau thai không rơi ra sau 4-6 giờ sau khi dê đẻ. Nếu để lâu có nguy cơ nhiễm trùng tử cung, viêm huyết và giảm khả năng sinh sản.",

  "causes": [
    "Dê đẻ khó, đẻ lâu.",
    "Thiếu khoáng - vitamin (đặc biệt Selenium, Vitamin E).",
    "Viêm tử cung trước đó.",
    "Dinh dưỡng kém cuối thai kỳ."
  ],

  "risk_factors": [
    "Dê già, dê sinh nhiều lứa.",
    "Thiếu khoáng lâu ngày.",
    "Đẻ trong chuồng ẩm bẩn.",
    "Không chăm sóc tốt cuối thai kỳ."
  ],

  "clinical_signs_detailed": [
    "Nhau lòi ra nhưng không rơi, kéo dài nhiều giờ.",
    "Âm hộ có dịch trong - đục.",
    "Dê khó chịu, ăn giảm.",
    "Nếu để lâu → dịch hôi, sốt, viêm tử cung."
  ],

  "clinical_signs_by_stage": {
    "mild": [
      "Nhau treo, dê vẫn ăn.",
      "Không sốt."
    ],
    "moderate": [
      "Nhau treo > 6 giờ.",
      "Ăn giảm, lờ đờ nhẹ."
    ],
    "severe": [
      "Dịch hôi, sốt, đau bụng.",
      "Chuyển sang viêm tử cung cấp."
    ]
  },

  "treatment": {
    "primary_drugs": [
      "Oxytocin (theo hướng dẫn thú y).",
      "Ceftiofur",
      "Amoxicillin"
    ],
    "alternative_drugs": [
      "Oxytetracycline",
      "Doxycycline"
    ],
    "note_drugs": [
      "Tuyệt đối KHÔNG tự tay kéo nhau mạnh vì dễ lộn tử cung hoặc chảy máu.",
      "Không thụt rửa bằng hóa chất mạnh."
    ],
    "symptomatic_treatment": {
      "antiinflammatory": [
        "Meloxicam",
        "Flunixin"
      ],
      "respiratory_support": [],
      "electrolyte": [
        "ORS",
        "Nước ấm dễ uống"
      ],
      "vitamin": [
        "Vitamin E - Selenium",
        "Vitamin C",
        "B-complex"
      ],
      "digestive_support": []
    },
    "supportive_care": [
      "Giữ khu vực đẻ sạch - khô.",
      "Không làm dê sợ hoặc stress.",
      "Theo dõi âm hộ và nhiệt độ mỗi 6-12 giờ.",
      "Bổ sung Selenium - Vitamin E định kỳ."
    ],
    "dose_policy": [
      "Oxytocin và kháng sinh phải dùng đúng theo nhãn hoặc thú y.",
      "Không lạm dụng oxytocin ở dê đẻ khó."
    ]
  },

  "severe_case_treatment": {
    "case_type_1": {
      "description": "Nhau treo nhưng dê chưa sốt.",
      "guideline": [
        "Dùng oxytocin theo thú y.",
        "Kháng sinh phòng nhiễm trùng.",
        "Vitamin E - Selenium."
      ]
    },
    "case_type_2": {
      "description": "Dịch hôi, sốt, nghi viêm tử cung.",
      "guideline": [
        "Ceftiofur/amoxicillin.",
        "Chống viêm + điện giải.",
        "Theo dõi sát tình trạng ăn - đứng.",
        "Gọi thú y khi không cải thiện."
      ]
    },
    "note": "Sót nhau là cửa ngõ dẫn đến viêm tử cung - xử lý càng sớm càng tốt."
  },

  "prevention": [
    "Bổ sung Selenium - Vitamin E trước khi đẻ.",
    "Dinh dưỡng đầy đủ cuối thai kỳ.",
    "Chuồng đẻ sạch, khô.",
    "Đỡ đẻ đúng kỹ thuật, tránh can thiệp thô bạo."
  ],

  "notes": [
    "Không kéo nhau bằng tay.",
    "Theo dõi dịch âm hộ 1-3 ngày sau đẻ."
  ],

  "disclaimer": "Ứng dụng chỉ mang tính tham khảo."
}
